cake.py
disco.py
heart.py
main.py
virus.py
aastha-0.1.0.data/data/dooron.wav
aastha-0.1.0.data/data/rabba.wav
aastha-0.1.0.dist-info/licenses/LICENSE
aastha-0.1.0.dist-info/METADATA
aastha-0.1.0.dist-info/WHEEL
aastha-0.1.0.dist-info/entry_points.txt
aastha-0.1.0.dist-info/top_level.txt
aastha-0.1.0.dist-info/RECORD
